switchbox/__init__.py
switchbox/__main__.py
switchbox/app.py
switchbox/cli.py
switchbox/ext/__init__.py
switchbox/ext/git.py
switchbox/repo.py
switchbox/tests/__init__.py
switchbox/tests/test_repo.py
switchbox-0.5.0.dist-info/METADATA
switchbox-0.5.0.dist-info/WHEEL
switchbox-0.5.0.dist-info/entry_points.txt
switchbox-0.5.0.dist-info/RECORD
