Metadata-Version: 2.1
Name: switchbox
Version: 0.5.0
Summary: Tools for working with Git repositories.
Home-page: https://pypi.org/project/switchbox/
License: MPL-2.0
Author: Sam Clements
Author-email: sam@borntyping.co.uk
Requires-Python: >=3.10,<4.0
Classifier: Development Status :: 5 - Production/Stable
Classifier: Environment :: Console
Classifier: License :: OSI Approved
Classifier: License :: OSI Approved :: Mozilla Public License 2.0 (MPL 2.0)
Classifier: Programming Language :: Python :: 3
Classifier: Programming Language :: Python :: 3.10
Classifier: Programming Language :: Python :: 3.11
Classifier: Programming Language :: Python :: 3.12
Classifier: Topic :: Software Development
Classifier: Topic :: Software Development :: Version Control
Classifier: Topic :: Software Development :: Version Control :: Git
Requires-Dist: GitPython (>=3.1.27,<4.0.0)
Requires-Dist: PyGithub (>=1.55,<2.0)
Requires-Dist: click (>=8.1.3,<9.0.0)
Requires-Dist: giturl (>=0.1.3,<0.2.0)
Requires-Dist: inflect (>=6.0.0,<7.0.0)
Requires-Dist: rich (>=12.5.1,<13.0.0)
Project-URL: Repository, https://github.com/borntyping/switchbox
